aws_profile_switcher/__init__.py
aws_profile_switcher/_version.py
aws_profile_switcher/run.py
aws_profile_switcher/common/__init__.py
aws_profile_switcher/common/common.py
aws_profile_switcher/switch_default/__init__.py
aws_profile_switcher/switch_default/switch.py
aws_profile_switcher/tests/__init__.py
aws_profile_switcher/tests/common.py
aws_profile_switcher/tests/switch.py
aws_profile_switcher-0.2.3.dist-info/LICENSE
aws_profile_switcher-0.2.3.dist-info/METADATA
aws_profile_switcher-0.2.3.dist-info/WHEEL
aws_profile_switcher-0.2.3.dist-info/entry_points.txt
aws_profile_switcher-0.2.3.dist-info/top_level.txt
aws_profile_switcher-0.2.3.dist-info/RECORD
