Metadata-Version: 2.1
Name: aws-profile-switcher
Version: 0.2.3
Summary: This util allows you to switch default AWS CLI profile
Home-page: https://github.com/99stealth/aws-profile-switcher
Author: Roman Banakh
Author-email: banakh.ri@gmail.com
License: MIT
Platform: UNKNOWN
Classifier: License :: OSI Approved :: MIT License
Classifier: Programming Language :: Python :: 3
Classifier: Programming Language :: Python :: 3.5
Classifier: Programming Language :: Python :: 3.6
Classifier: Programming Language :: Python :: 3.7
Classifier: Programming Language :: Python :: 3.8
Requires-Dist: configparser
Requires-Dist: argparse
